CONTRIBUTORS.md
LICENSE.txt
MANIFEST.in
README.md
setup.cfg
setup.py
FALCONN.egg-info/PKG-INFO
FALCONN.egg-info/SOURCES.txt
FALCONN.egg-info/dependency_links.txt
FALCONN.egg-info/top_level.txt
external/eigen/Eigen/CMakeLists.txt
external/eigen/Eigen/Cholesky
external/eigen/Eigen/CholmodSupport
external/eigen/Eigen/Core
external/eigen/Eigen/Dense
external/eigen/Eigen/Eigen
external/eigen/Eigen/Eigenvalues
external/eigen/Eigen/Geometry
external/eigen/Eigen/Householder
external/eigen/Eigen/IterativeLinearSolvers
external/eigen/Eigen/Jacobi
external/eigen/Eigen/LU
external/eigen/Eigen/MetisSupport
external/eigen/Eigen/OrderingMethods
external/eigen/Eigen/PaStiXSupport
external/eigen/Eigen/PardisoSupport
external/eigen/Eigen/QR
external/eigen/Eigen/QtAlignedMalloc
external/eigen/Eigen/SPQRSupport
external/eigen/Eigen/SVD
external/eigen/Eigen/Sparse
external/eigen/Eigen/SparseCholesky
external/eigen/Eigen/SparseCore
external/eigen/Eigen/SparseLU
external/eigen/Eigen/SparseQR
external/eigen/Eigen/StdDeque
external/eigen/Eigen/StdList
external/eigen/Eigen/StdVector
external/eigen/Eigen/SuperLUSupport
external/eigen/Eigen/UmfPackSupport
external/eigen/Eigen/src/Cholesky/LDLT.h
external/eigen/Eigen/src/Cholesky/LLT.h
external/eigen/Eigen/src/Cholesky/LLT_LAPACKE.h
external/eigen/Eigen/src/CholmodSupport/CholmodSupport.h
external/eigen/Eigen/src/Core/Array.h
external/eigen/Eigen/src/Core/ArrayBase.h
external/eigen/Eigen/src/Core/ArrayWrapper.h
external/eigen/Eigen/src/Core/Assign.h
external/eigen/Eigen/src/Core/AssignEvaluator.h
external/eigen/Eigen/src/Core/Assign_MKL.h
external/eigen/Eigen/src/Core/BandMatrix.h
external/eigen/Eigen/src/Core/Block.h
external/eigen/Eigen/src/Core/BooleanRedux.h
external/eigen/Eigen/src/Core/CommaInitializer.h
external/eigen/Eigen/src/Core/ConditionEstimator.h
external/eigen/Eigen/src/Core/CoreEvaluators.h
external/eigen/Eigen/src/Core/CoreIterators.h
external/eigen/Eigen/src/Core/CwiseBinaryOp.h
external/eigen/Eigen/src/Core/CwiseNullaryOp.h
external/eigen/Eigen/src/Core/CwiseTernaryOp.h
external/eigen/Eigen/src/Core/CwiseUnaryOp.h
