Metadata-Version: 1.0
Name: FALCONN
Version: 1.3.1
Summary: A library for similarity search over high-dimensional data based on Locality-Sensitive Hashing (LSH)
Home-page: http://falconn-lib.org/
Author: Ilya Razenshteyn, Ludwig Schmidt
Author-email: falconn.lib@gmail.com
License: MIT
Keywords: nearest neighbor search similarity lsh locality-sensitive hashing cosine distance euclidean
Platform: UNKNOWN
